python_asana/__init__.py
python_asana/api.py
python_asana/config/prod.yaml
python_asana-0.1.0.dist-info/METADATA
python_asana-0.1.0.dist-info/WHEEL
python_asana-0.1.0.dist-info/licenses/LICENSE
python_asana-0.1.0.dist-info/RECORD
