Metadata-Version: 2.3
Name: python-asana
Version: 0.1.0
Summary: Add your description here
License-File: LICENSE
Requires-Python: >=3.9
Requires-Dist: pyyaml>=6.0.2
Requires-Dist: requests>=2.32.3
